damCalculator/__init__.py
damCalculator/model.py
damCalculator/analysis/__init__.py
damCalculator/analysis/safetyFactors.py
damCalculator/force/__init__.py
damCalculator/force/forces.py
damCalculator/geometry/__init__.py
damCalculator/geometry/damGeometry.py
damCalculator/geometry/sectionProperty.py
damCalculator/material/__init__.py
damCalculator/material/materials.py
damCalculator/plot/__init__.py
damCalculator/plot/plotForce.py
damCalculator/plot/plotGeometry.py
damcalculator-0.0.1.dist-info/LICENSE
damcalculator-0.0.1.dist-info/METADATA
damcalculator-0.0.1.dist-info/WHEEL
damcalculator-0.0.1.dist-info/top_level.txt
damcalculator-0.0.1.dist-info/RECORD
