Metadata-Version: 2.1
Name: damcalculator
Version: 0.0.1
Summary: A dam calculator
Home-page: https://github.com/YingnanXuUCB/damCalculator
Author: YingnanXu
Author-email: yingnanxu@berkeley.edu
License: UNKNOWN
Platform: UNKNOWN
Classifier: Programming Language :: Python :: 3
Classifier: License :: OSI Approved :: MIT License
Classifier: Operating System :: OS Independent
Requires-Python: >=3.5
